sphinx/example_images.py
sphinx/release_note.py
sphinx/source/conf.py
test/test_api.py
test/test_logging.py
zhl/__init__.py
zhl/algorithm/__init__.py
zhl/algorithm/bisect.py
zhl/algorithm/collections.py
zhl/algorithm/fft.py
zhl/algorithm/graph.py
zhl/algorithm/prime.py
zhl/algorithm/sort.py
zhl/api/__init__.py
zhl/api/discord.py
zhl/api/github.py
zhl/api/koreainvestment.py
zhl/api/open_ai.py
zhl/api/slack.py
zhl/logging/__init__.py
zhl/logging/handler.py
zhl/logging/logger.py
zhl/mlops/__init__.py
zhl/mlops/cli.py
zhl/mlops/triton.py
zhl/monitoring/__init__.py
zhl/monitoring/cpu.py
zhl/monitoring/gpu.py
zhl/monitoring/storage.py
zhl/plot/__init__.py
zhl/plot/bar_chart.py
zhl/plot/pie.py
zhl/plot/plot.py
zhl/plot/scatter.py
zhl/plot/table.py
zhl/plot/util.py
zhl/plot/fonts/NotoSerifKR-Medium.otf
zhl/plot/fonts/times.ttf
zhl/quant/__init__.py
zhl/quant/backtest.py
zhl/quant/methods.py
zhl/quant/quant.py
zhl/quant/util.py
zhl/util/__init__.py
zhl/util/csv.py
zhl/util/data.py
zhl/util/json.py
zhl/vision/__init__.py
zhl/vision/cli.py
zhl/vision/compare.py
zhl/vision/convert.py
zhl/vision/data.py
zhl/vision/eval.py
zhl/vision/gif.py
zhl/vision/loader.py
zhl/vision/transform.py
zhl/vision/util.py
zhl/vision/visual.py
zhl_test-1.1.3.dist-info/LICENSE
zhl_test-1.1.3.dist-info/METADATA
zhl_test-1.1.3.dist-info/WHEEL
zhl_test-1.1.3.dist-info/entry_points.txt
zhl_test-1.1.3.dist-info/top_level.txt
zhl_test-1.1.3.dist-info/RECORD
