Metadata-Version: 2.1
Name: zhl-test
Version: 1.1.3
Summary: Zerohertz's Library
Author-email: zerohertz <ohg3417@gmail.com>
Maintainer-email: zerohertz <ohg3417@gmail.com>
License: MIT
Project-URL: homepage, https://zerohertz.github.io/zhl
Project-URL: documentation, https://zerohertz.github.io/zhl
Project-URL: repository, https://github.com/Zerohertz/zhl
Project-URL: changelog, https://zerohertz.github.io/zhl/release.html
Keywords: Scientific/Engineering,Mathematics,Artificial Intelligence,Software Development,Libraries
Classifier: Development Status :: 5 - Production/Stable
Classifier: Intended Audience :: Developers
Classifier: Intended Audience :: Education
Classifier: Intended Audience :: Science/Research
Classifier: Topic :: Scientific/Engineering
Classifier: Topic :: Scientific/Engineering :: Mathematics
Classifier: Topic :: Scientific/Engineering :: Artificial Intelligence
Classifier: Topic :: Software Development
Classifier: Topic :: Software Development :: Libraries
Classifier: Topic :: Software Development :: Libraries :: Python Modules
Classifier: Programming Language :: Python
Classifier: Programming Language :: Python :: 3
Requires-Python: >=3.7
License-File: LICENSE
Requires-Dist: psutil
Requires-Dist: matplotlib >=3.5.2
Requires-Dist: seaborn >=0.12
Requires-Dist: pandas
Requires-Dist: mplfinance
Requires-Dist: tqdm
Requires-Dist: orjson
Requires-Dist: numpy
Requires-Dist: opencv-python
Requires-Dist: Pillow >=10.0.0
Requires-Dist: shapely
Provides-Extra: all
Requires-Dist: requests ; extra == 'all'
Requires-Dist: openai ; extra == 'all'
Requires-Dist: slack-sdk ; extra == 'all'
Requires-Dist: rich ; extra == 'all'
Requires-Dist: prettytable ; extra == 'all'
Requires-Dist: protobuf ; extra == 'all'
Requires-Dist: tritonclient[grpc] >=2.44.0 ; extra == 'all'
Requires-Dist: plotly ; extra == 'all'
Requires-Dist: beautifulsoup4 ; extra == 'all'
Requires-Dist: finance-datareader ; extra == 'all'
Provides-Extra: api
Requires-Dist: requests ; extra == 'api'
Requires-Dist: openai ; extra == 'api'
Requires-Dist: slack-sdk ; extra == 'api'
Requires-Dist: rich ; extra == 'api'
Provides-Extra: mlops
Requires-Dist: requests ; extra == 'mlops'
Requires-Dist: openai ; extra == 'mlops'
Requires-Dist: slack-sdk ; extra == 'mlops'
Requires-Dist: rich ; extra == 'mlops'
Requires-Dist: protobuf ; extra == 'mlops'
Requires-Dist: tritonclient[grpc] >=2.44.0 ; extra == 'mlops'
Requires-Dist: prettytable ; extra == 'mlops'
Provides-Extra: quant
Requires-Dist: requests ; extra == 'quant'
Requires-Dist: openai ; extra == 'quant'
Requires-Dist: slack-sdk ; extra == 'quant'
Requires-Dist: rich ; extra == 'quant'
Requires-Dist: plotly ; extra == 'quant'
Requires-Dist: beautifulsoup4 ; extra == 'quant'
Requires-Dist: finance-datareader ; extra == 'quant'
Requires-Dist: prettytable ; extra == 'quant'
